[{"trade_date":"2026-05-12","etf_code":"00401A","stock_code":"2303","stock_name":"UNITED MICROELECTRONICS CORP","action":"DECREASE","weight_before":2.02,"weight_after":1.73,"weight_change":-0.29,"shares_change":-174000.0,"close_price":95.0,"amount_change":-16530000.0},{"trade_date":"2026-05-12","etf_code":"00401A","stock_code":"2886","stock_name":"MEGA FINANCIAL HOLDING CO LT","action":"DECREASE","weight_before":0.76,"weight_after":0.47,"weight_change":-0.29,"shares_change":-248000.0,"close_price":40.1,"amount_change":-9944800.0},{"trade_date":"2026-05-12","etf_code":"00401A","stock_code":"2890","stock_name":"SINOPAC FINANCIAL HOLDINGS","action":"DECREASE","weight_before":0.43,"weight_after":0.25,"weight_change":-0.18,"shares_change":-216000.0,"close_price":30.6,"amount_change":-6609600.0},{"trade_date":"2026-05-12","etf_code":"00401A","stock_code":"3008","stock_name":"LARGAN PRECISION CO LTD","action":"DECREASE","weight_before":0.29,"weight_after":0.08,"weight_change":-0.21,"shares_change":-3000.0,"close_price":2545.0,"amount_change":-7635000.0},{"trade_date":"2026-05-12","etf_code":"00401A","stock_code":"3131","stock_name":"GRAND PROCESS TECHNOLOGY COR","action":"DECREASE","weight_before":0.69,"weight_after":0.53,"weight_change":-0.16,"shares_change":-2000.0,"close_price":3140.0,"amount_change":-6280000.0},{"trade_date":"2026-05-12","etf_code":"00401A","stock_code":"5347","stock_name":"VANGUARD INTERNATIONAL SEMI","action":"DECREASE","weight_before":1.43,"weight_after":1.13,"weight_change":-0.3,"shares_change":-57000.0,"close_price":170.0,"amount_change":-9690000.0},{"trade_date":"2026-05-12","etf_code":"00401A","stock_code":"6510","stock_name":"CHUNGHWA PRECISION TEST TECH","action":"NEW_BUY","weight_before":0.0,"weight_after":0.66,"weight_change":0.66,"shares_change":6000.0,"close_price":3860.0,"amount_change":23160000.0},{"trade_date":"2026-05-12","etf_code":"00401A","stock_code":"6515","stock_name":"WINWAY TECHNOLOGY CO LTD","action":"DECREASE","weight_before":1.13,"weight_after":0.85,"weight_change":-0.28,"shares_change":-1000.0,"close_price":10090.0,"amount_change":-10090000.0},{"trade_date":"2026-05-12","etf_code":"00401A","stock_code":"8021","stock_name":"TOPOINT TECHNOLOGY CO LTD","action":"DECREASE","weight_before":0.82,"weight_after":0.71,"weight_change":-0.11,"shares_change":-15000.0,"close_price":429.0,"amount_change":-6435000.0},{"trade_date":"2026-05-12","etf_code":"00403A","stock_code":"1560","stock_name":"中砂","action":"NEW_BUY","weight_before":0.0,"weight_after":0.48,"weight_change":0.48,"shares_change":850000.0,"close_price":629.0,"amount_change":534650000.0},{"trade_date":"2026-05-12","etf_code":"00403A","stock_code":"2049","stock_name":"上銀","action":"NEW_BUY","weight_before":0.0,"weight_after":0.09,"weight_change":0.09,"shares_change":300000.0,"close_price":351.0,"amount_change":105300000.0},{"trade_date":"2026-05-12","etf_code":"00403A","stock_code":"2303","stock_name":"聯電","action":"NEW_BUY","weight_before":0.0,"weight_after":3.79,"weight_change":3.79,"shares_change":42695000.0,"close_price":95.0,"amount_change":4056025000.0},{"trade_date":"2026-05-12","etf_code":"00403A","stock_code":"2308","stock_name":"台達電","action":"NEW_BUY","weight_before":0.0,"weight_after":3.4,"weight_change":3.4,"shares_change":1823000.0,"close_price":2245.0,"amount_change":4092635000.0},{"trade_date":"2026-05-12","etf_code":"00403A","stock_code":"2313","stock_name":"華通","action":"NEW_BUY","weight_before":0.0,"weight_after":0.6,"weight_change":0.6,"shares_change":2731000.0,"close_price":242.0,"amount_change":660902000.0},{"trade_date":"2026-05-12","etf_code":"00403A","stock_code":"2327","stock_name":"國巨*","action":"NEW_BUY","weight_before":0.0,"weight_after":0.66,"weight_change":0.66,"shares_change":1860000.0,"close_price":391.5,"amount_change":728190000.0},{"trade_date":"2026-05-12","etf_code":"00403A","stock_code":"2330","stock_name":"台積電","action":"NEW_BUY","weight_before":0.0,"weight_after":13.49,"weight_change":13.49,"shares_change":7040000.0,"close_price":2235.0,"amount_change":15734400000.0},{"trade_date":"2026-05-12","etf_code":"00403A","stock_code":"2337","stock_name":"旺宏","action":"NEW_BUY","weight_before":0.0,"weight_after":0.43,"weight_change":0.43,"shares_change":3300000.0,"close_price":159.5,"amount_change":526350000.0},{"trade_date":"2026-05-12","etf_code":"00403A","stock_code":"2345","stock_name":"智邦","action":"NEW_BUY","weight_before":0.0,"weight_after":2.64,"weight_change":2.64,"shares_change":1230000.0,"close_price":2590.0,"amount_change":3185700000.0},{"trade_date":"2026-05-12","etf_code":"00403A","stock_code":"2360","stock_name":"致茂","action":"NEW_BUY","weight_before":0.0,"weight_after":1.06,"weight_change":1.06,"shares_change":509000.0,"close_price":2360.0,"amount_change":1201240000.0},{"trade_date":"2026-05-12","etf_code":"00403A","stock_code":"2368","stock_name":"金像電","action":"NEW_BUY","weight_before":0.0,"weight_after":2.29,"weight_change":2.29,"shares_change":1941000.0,"close_price":1400.0,"amount_change":2717400000.0},{"trade_date":"2026-05-12","etf_code":"00403A","stock_code":"2383","stock_name":"台光電","action":"NEW_BUY","weight_before":0.0,"weight_after":4.11,"weight_change":4.11,"shares_change":986000.0,"close_price":4850.0,"amount_change":4782100000.0},{"trade_date":"2026-05-12","etf_code":"00403A","stock_code":"2454","stock_name":"聯發科","action":"NEW_BUY","weight_before":0.0,"weight_after":0.49,"weight_change":0.49,"shares_change":155000.0,"close_price":3880.0,"amount_change":601400000.0},{"trade_date":"2026-05-12","etf_code":"00403A","stock_code":"2455","stock_name":"全新","action":"NEW_BUY","weight_before":0.0,"weight_after":0.05,"weight_change":0.05,"shares_change":145000.0,"close_price":360.0,"amount_change":52200000.0},{"trade_date":"2026-05-12","etf_code":"00403A","stock_code":"2481","stock_name":"強茂","action":"NEW_BUY","weight_before":0.0,"weight_after":0.08,"weight_change":0.08,"shares_change":830000.0,"close_price":109.0,"amount_change":90470000.0},{"trade_date":"2026-05-12","etf_code":"00403A","stock_code":"2882","stock_name":"國泰金","action":"NEW_BUY","weight_before":0.0,"weight_after":0.45,"weight_change":0.45,"shares_change":7000000.0,"close_price":78.4,"amount_change":548800000.0},{"trade_date":"2026-05-12","etf_code":"00403A","stock_code":"2891","stock_name":"中信金","action":"NEW_BUY","weight_before":0.0,"weight_after":0.08,"weight_change":0.08,"shares_change":1800000.0,"close_price":55.3,"amount_change":99540000.0},{"trade_date":"2026-05-12","etf_code":"00403A","stock_code":"3017","stock_name":"奇鋐","action":"NEW_BUY","weight_before":0.0,"weight_after":4.01,"weight_change":4.01,"shares_change":1871000.0,"close_price":2555.0,"amount_change":4780405000.0},{"trade_date":"2026-05-12","etf_code":"00403A","stock_code":"3036","stock_name":"文曄","action":"NEW_BUY","weight_before":0.0,"weight_after":0.48,"weight_change":0.48,"shares_change":2065000.0,"close_price":264.5,"amount_change":546192500.0},{"trade_date":"2026-05-12","etf_code":"00403A","stock_code":"3037","stock_name":"欣興","action":"NEW_BUY","weight_before":0.0,"weight_after":3.41,"weight_change":3.41,"shares_change":4589000.0,"close_price":861.0,"amount_change":3951129000.0},{"trade_date":"2026-05-12","etf_code":"00403A","stock_code":"3044","stock_name":"健鼎","action":"NEW_BUY","weight_before":0.0,"weight_after":0.72,"weight_change":0.72,"shares_change":1756000.0,"close_price":489.5,"amount_change":859562000.0},{"trade_date":"2026-05-12","etf_code":"00403A","stock_code":"3081","stock_name":"聯亞","action":"NEW_BUY","weight_before":0.0,"weight_after":0.66,"weight_change":0.66,"shares_change":255000.0,"close_price":3055.0,"amount_change":779025000.0},{"trade_date":"2026-05-12","etf_code":"00403A","stock_code":"3105","stock_name":"穩懋","action":"NEW_BUY","weight_before":0.0,"weight_after":0.33,"weight_change":0.33,"shares_change":757000.0,"close_price":512.0,"amount_change":387584000.0},{"trade_date":"2026-05-12","etf_code":"00403A","stock_code":"3211","stock_name":"順達","action":"NEW_BUY","weight_before":0.0,"weight_after":0.44,"weight_change":0.44,"shares_change":1300000.0,"close_price":402.0,"amount_change":522600000.0},{"trade_date":"2026-05-12","etf_code":"00403A","stock_code":"3443","stock_name":"創意","action":"NEW_BUY","weight_before":0.0,"weight_after":0.54,"weight_change":0.54,"shares_change":114000.0,"close_price":5730.0,"amount_change":653220000.0},{"trade_date":"2026-05-12","etf_code":"00403A","stock_code":"3529","stock_name":"力旺","action":"NEW_BUY","weight_before":0.0,"weight_after":0.76,"weight_change":0.76,"shares_change":217000.0,"close_price":4115.0,"amount_change":892955000.0},{"trade_date":"2026-05-12","etf_code":"00403A","stock_code":"3533","stock_name":"嘉澤","action":"NEW_BUY","weight_before":0.0,"weight_after":1.32,"weight_change":1.32,"shares_change":555000.0,"close_price":2845.0,"amount_change":1578975000.0},{"trade_date":"2026-05-12","etf_code":"00403A","stock_code":"3583","stock_name":"辛耘","action":"NEW_BUY","weight_before":0.0,"weight_after":0.52,"weight_change":0.52,"shares_change":641000.0,"close_price":866.0,"amount_change":555106000.0},{"trade_date":"2026-05-12","etf_code":"00403A","stock_code":"3653","stock_name":"健策","action":"NEW_BUY","weight_before":0.0,"weight_after":1.43,"weight_change":1.43,"shares_change":430000.0,"close_price":4015.0,"amount_change":1726450000.0},{"trade_date":"2026-05-12","etf_code":"00403A","stock_code":"3665","stock_name":"貿聯-KY","action":"NEW_BUY","weight_before":0.0,"weight_after":2.5,"weight_change":2.5,"shares_change":1060000.0,"close_price":2905.0,"amount_change":3079300000.0},{"trade_date":"2026-05-12","etf_code":"00403A","stock_code":"3711","stock_name":"日月光投控","action":"NEW_BUY","weight_before":0.0,"weight_after":3.26,"weight_change":3.26,"shares_change":6920000.0,"close_price":537.0,"amount_change":3716040000.0},{"trade_date":"2026-05-12","etf_code":"00403A","stock_code":"4958","stock_name":"臻鼎-KY","action":"NEW_BUY","weight_before":0.0,"weight_after":0.79,"weight_change":0.79,"shares_change":2280000.0,"close_price":412.0,"amount_change":939360000.0},{"trade_date":"2026-05-12","etf_code":"00403A","stock_code":"4966","stock_name":"譜瑞-KY","action":"NEW_BUY","weight_before":0.0,"weight_after":0.46,"weight_change":0.46,"shares_change":704000.0,"close_price":761.0,"amount_change":535744000.0},{"trade_date":"2026-05-12","etf_code":"00403A","stock_code":"4979","stock_name":"華星光","action":"NEW_BUY","weight_before":0.0,"weight_after":0.48,"weight_change":0.48,"shares_change":860000.0,"close_price":659.0,"amount_change":566740000.0},{"trade_date":"2026-05-12","etf_code":"00403A","stock_code":"5274","stock_name":"信驊","action":"NEW_BUY","weight_before":0.0,"weight_after":1.58,"weight_change":1.58,"shares_change":103000.0,"close_price":18005.0,"amount_change":1854515000.0},{"trade_date":"2026-05-12","etf_code":"00403A","stock_code":"5347","stock_name":"世界","action":"NEW_BUY","weight_before":0.0,"weight_after":1.43,"weight_change":1.43,"shares_change":9900000.0,"close_price":170.0,"amount_change":1683000000.0},{"trade_date":"2026-05-12","etf_code":"00403A","stock_code":"6147","stock_name":"頎邦","action":"NEW_BUY","weight_before":0.0,"weight_after":0.48,"weight_change":0.48,"shares_change":2900000.0,"close_price":196.0,"amount_change":568400000.0},{"trade_date":"2026-05-12","etf_code":"00403A","stock_code":"6223","stock_name":"旺矽","action":"NEW_BUY","weight_before":0.0,"weight_after":1.21,"weight_change":1.21,"shares_change":260000.0,"close_price":5480.0,"amount_change":1424800000.0},{"trade_date":"2026-05-12","etf_code":"00403A","stock_code":"6274","stock_name":"台燿","action":"NEW_BUY","weight_before":0.0,"weight_after":0.68,"weight_change":0.68,"shares_change":551000.0,"close_price":1450.0,"amount_change":798950000.0},{"trade_date":"2026-05-12","etf_code":"00403A","stock_code":"6442","stock_name":"光聖","action":"NEW_BUY","weight_before":0.0,"weight_after":0.11,"weight_change":0.11,"shares_change":67000.0,"close_price":1950.0,"amount_change":130650000.0},{"trade_date":"2026-05-12","etf_code":"00403A","stock_code":"6515","stock_name":"穎崴","action":"NEW_BUY","weight_before":0.0,"weight_after":0.67,"weight_change":0.67,"shares_change":79000.0,"close_price":10090.0,"amount_change":797110000.0},{"trade_date":"2026-05-12","etf_code":"00403A","stock_code":"6669","stock_name":"緯穎","action":"NEW_BUY","weight_before":0.0,"weight_after":2.44,"weight_change":2.44,"shares_change":496000.0,"close_price":5340.0,"amount_change":2648640000.0},{"trade_date":"2026-05-12","etf_code":"00403A","stock_code":"6805","stock_name":"富世達","action":"NEW_BUY","weight_before":0.0,"weight_after":0.18,"weight_change":0.18,"shares_change":115000.0,"close_price":1995.0,"amount_change":229425000.0},{"trade_date":"2026-05-12","etf_code":"00403A","stock_code":"7769","stock_name":"鴻勁","action":"NEW_BUY","weight_before":0.0,"weight_after":0.29,"weight_change":0.29,"shares_change":50000.0,"close_price":6380.0,"amount_change":319000000.0},{"trade_date":"2026-05-12","etf_code":"00403A","stock_code":"8046","stock_name":"南電","action":"NEW_BUY","weight_before":0.0,"weight_after":1.98,"weight_change":1.98,"shares_change":2590000.0,"close_price":908.0,"amount_change":2351720000.0},{"trade_date":"2026-05-12","etf_code":"00403A","stock_code":"8210","stock_name":"勤誠","action":"NEW_BUY","weight_before":0.0,"weight_after":0.68,"weight_change":0.68,"shares_change":513000.0,"close_price":1555.0,"amount_change":797715000.0},{"trade_date":"2026-05-12","etf_code":"00403A","stock_code":"8299","stock_name":"群聯","action":"NEW_BUY","weight_before":0.0,"weight_after":2.61,"weight_change":2.61,"shares_change":1128000.0,"close_price":2725.0,"amount_change":3073800000.0},{"trade_date":"2026-05-12","etf_code":"00403A","stock_code":"8358","stock_name":"金居","action":"NEW_BUY","weight_before":0.0,"weight_after":0.55,"weight_change":0.55,"shares_change":1350000.0,"close_price":477.0,"amount_change":643950000.0},{"trade_date":"2026-05-12","etf_code":"00403A","stock_code":"8996","stock_name":"高力","action":"NEW_BUY","weight_before":0.0,"weight_after":0.75,"weight_change":0.75,"shares_change":833000.0,"close_price":1055.0,"amount_change":878815000.0},{"trade_date":"2026-05-12","etf_code":"00981A","stock_code":"2313","stock_name":"華通","action":"INCREASE","weight_before":0.23,"weight_after":0.39,"weight_change":0.16,"shares_change":1500000.0,"close_price":242.0,"amount_change":363000000.0},{"trade_date":"2026-05-12","etf_code":"00981A","stock_code":"2317","stock_name":"鴻海","action":"DECREASE","weight_before":1.3,"weight_after":0.33,"weight_change":-0.97,"shares_change":-10565000.0,"close_price":252.0,"amount_change":-2662380000.0},{"trade_date":"2026-05-12","etf_code":"00981A","stock_code":"2330","stock_name":"台積電","action":"INCREASE","weight_before":9.23,"weight_after":9.63,"weight_change":0.4,"shares_change":298000.0,"close_price":2235.0,"amount_change":666030000.0},{"trade_date":"2026-05-12","etf_code":"00981A","stock_code":"3008","stock_name":"大立光","action":"NEW_BUY","weight_before":0.0,"weight_after":0.16,"weight_change":0.16,"shares_change":159000.0,"close_price":2545.0,"amount_change":404655000.0},{"trade_date":"2026-05-12","etf_code":"00981A","stock_code":"3017","stock_name":"奇鋐","action":"INCREASE","weight_before":4.04,"weight_after":4.13,"weight_change":0.09,"shares_change":117000.0,"close_price":2555.0,"amount_change":298935000.0},{"trade_date":"2026-05-12","etf_code":"00981A","stock_code":"3037","stock_name":"欣興","action":"INCREASE","weight_before":3.25,"weight_after":3.47,"weight_change":0.22,"shares_change":435000.0,"close_price":861.0,"amount_change":374535000.0},{"trade_date":"2026-05-12","etf_code":"00981A","stock_code":"3711","stock_name":"日月光投控","action":"INCREASE","weight_before":2.7,"weight_after":3.05,"weight_change":0.35,"shares_change":1165000.0,"close_price":537.0,"amount_change":625605000.0},{"trade_date":"2026-05-12","etf_code":"00981A","stock_code":"6669","stock_name":"緯穎","action":"INCREASE","weight_before":3.97,"weight_after":4.87,"weight_change":0.9,"shares_change":247000.0,"close_price":5340.0,"amount_change":1318980000.0},{"trade_date":"2026-05-12","etf_code":"00982A","stock_code":"3491","stock_name":"昇達科","action":"INCREASE","weight_before":3.2,"weight_after":3.44,"weight_change":0.24,"shares_change":100000.0,"close_price":1765.0,"amount_change":176500000.0},{"trade_date":"2026-05-12","etf_code":"00982A","stock_code":"6139","stock_name":"亞翔","action":"DECREASE","weight_before":3.58,"weight_after":3.06,"weight_change":-0.52,"shares_change":-360000.0,"close_price":679.0,"amount_change":-244440000.0},{"trade_date":"2026-05-12","etf_code":"00982A","stock_code":"6285","stock_name":"啟碁","action":"INCREASE","weight_before":1.79,"weight_after":2.31,"weight_change":0.52,"shares_change":636000.0,"close_price":259.0,"amount_change":164724000.0},{"trade_date":"2026-05-12","etf_code":"00984A","stock_code":"1216","stock_name":"統一","action":"INCREASE","weight_before":0.82,"weight_after":0.89,"weight_change":0.07,"shares_change":72000.0,"close_price":73.9,"amount_change":5320800.0},{"trade_date":"2026-05-12","etf_code":"00984A","stock_code":"1785","stock_name":"光洋科","action":"INCREASE","weight_before":0.76,"weight_after":0.83,"weight_change":0.07,"shares_change":31000.0,"close_price":158.5,"amount_change":4913500.0},{"trade_date":"2026-05-12","etf_code":"00984A","stock_code":"2360","stock_name":"致茂","action":"INCREASE","weight_before":1.76,"weight_after":1.89,"weight_change":0.13,"shares_change":2000.0,"close_price":2360.0,"amount_change":4720000.0},{"trade_date":"2026-05-12","etf_code":"00984A","stock_code":"2379","stock_name":"瑞昱","action":"DECREASE","weight_before":1.8,"weight_after":1.73,"weight_change":-0.07,"shares_change":3000.0,"close_price":584.0,"amount_change":1752000.0},{"trade_date":"2026-05-12","etf_code":"00984A","stock_code":"2881","stock_name":"富邦金控","action":"DECREASE","weight_before":3.67,"weight_after":3.61,"weight_change":-0.06,"shares_change":17000.0,"close_price":95.5,"amount_change":1623500.0},{"trade_date":"2026-05-12","etf_code":"00984A","stock_code":"2882","stock_name":"國泰金","action":"DECREASE","weight_before":3.14,"weight_after":3.07,"weight_change":-0.07,"shares_change":11000.0,"close_price":78.4,"amount_change":862400.0},{"trade_date":"2026-05-12","etf_code":"00984A","stock_code":"2883","stock_name":"凱基金控","action":"DECREASE","weight_before":2.06,"weight_after":1.96,"weight_change":-0.1,"shares_change":39000.0,"close_price":22.8,"amount_change":889200.0},{"trade_date":"2026-05-12","etf_code":"00984A","stock_code":"2891","stock_name":"中信金","action":"DECREASE","weight_before":3.07,"weight_after":2.99,"weight_change":-0.08,"shares_change":39000.0,"close_price":55.3,"amount_change":2156700.0},{"trade_date":"2026-05-12","etf_code":"00984A","stock_code":"3189","stock_name":"景碩科技","action":"INCREASE","weight_before":1.25,"weight_after":1.36,"weight_change":0.11,"shares_change":19000.0,"close_price":503.0,"amount_change":9557000.0},{"trade_date":"2026-05-12","etf_code":"00984A","stock_code":"3374","stock_name":"精材","action":"INCREASE","weight_before":0.43,"weight_after":0.53,"weight_change":0.1,"shares_change":24000.0,"close_price":255.5,"amount_change":6132000.0},{"trade_date":"2026-05-12","etf_code":"00984A","stock_code":"3443","stock_name":"創意電子","action":"INCREASE","weight_before":0.25,"weight_after":0.41,"weight_change":0.16,"shares_change":2000.0,"close_price":5730.0,"amount_change":11460000.0},{"trade_date":"2026-05-12","etf_code":"00984A","stock_code":"3563","stock_name":"牧德","action":"INCREASE","weight_before":0.34,"weight_after":0.39,"weight_change":0.05,"shares_change":4000.0,"close_price":807.0,"amount_change":3228000.0},{"trade_date":"2026-05-12","etf_code":"00984A","stock_code":"6217","stock_name":"中國探針","action":"FULL_SELL","weight_before":0.52,"weight_after":0.0,"weight_change":-0.52,"shares_change":-126000.0,"close_price":310.0,"amount_change":-39060000.0},{"trade_date":"2026-05-12","etf_code":"00984A","stock_code":"6515","stock_name":"穎崴","action":"INCREASE","weight_before":1.18,"weight_after":1.31,"weight_change":0.13,"shares_change":1000.0,"close_price":10090.0,"amount_change":10090000.0},{"trade_date":"2026-05-12","etf_code":"00984A","stock_code":"6531","stock_name":"愛普科技","action":"FULL_SELL","weight_before":0.85,"weight_after":0.0,"weight_change":-0.85,"shares_change":-60000.0,"close_price":962.0,"amount_change":-57720000.0},{"trade_date":"2026-05-12","etf_code":"00984A","stock_code":"8021","stock_name":"尖點","action":"FULL_SELL","weight_before":1.18,"weight_after":0.0,"weight_change":-1.18,"shares_change":-188000.0,"close_price":429.0,"amount_change":-80652000.0},{"trade_date":"2026-05-12","etf_code":"00984A","stock_code":"8155","stock_name":"博智電子","action":"INCREASE","weight_before":0.37,"weight_after":0.45,"weight_change":0.08,"shares_change":13000.0,"close_price":420.0,"amount_change":5460000.0},{"trade_date":"2026-05-12","etf_code":"00984A","stock_code":"8210","stock_name":"勤誠興業","action":"INCREASE","weight_before":0.11,"weight_after":0.2,"weight_change":0.09,"shares_change":4000.0,"close_price":1555.0,"amount_change":6220000.0},{"trade_date":"2026-05-12","etf_code":"00987A","stock_code":"3443","stock_name":"創意","action":"DECREASE","weight_before":4.67,"weight_after":2.96,"weight_change":-1.71,"shares_change":-10000.0,"close_price":5730.0,"amount_change":-57300000.0},{"trade_date":"2026-05-12","etf_code":"00987A","stock_code":"6781","stock_name":"AES-KY","action":"INCREASE","weight_before":1.0,"weight_after":1.51,"weight_change":0.51,"shares_change":15000.0,"close_price":1320.0,"amount_change":19800000.0},{"trade_date":"2026-05-12","etf_code":"00988A","stock_code":"7769","stock_name":"鴻勁","action":"NEW_BUY","weight_before":0.0,"weight_after":0.27,"weight_change":0.27,"shares_change":14000.0,"close_price":6380.0,"amount_change":89320000.0},{"trade_date":"2026-05-12","etf_code":"00991A","stock_code":"2327","stock_name":"國巨股份","action":"INCREASE","weight_before":3.96,"weight_after":4.47,"weight_change":0.51,"shares_change":300000.0,"close_price":391.5,"amount_change":117450000.0},{"trade_date":"2026-05-12","etf_code":"00991A","stock_code":"2404","stock_name":"漢唐集成","action":"FULL_SELL","weight_before":0.78,"weight_after":0.0,"weight_change":-0.78,"shares_change":-329000.0,"close_price":1025.0,"amount_change":-337225000.0},{"trade_date":"2026-05-12","etf_code":"00991A","stock_code":"2408","stock_name":"南亞科技","action":"INCREASE","weight_before":4.71,"weight_after":5.16,"weight_change":0.45,"shares_change":300000.0,"close_price":301.0,"amount_change":90300000.0},{"trade_date":"2026-05-12","etf_code":"00991A","stock_code":"3324","stock_name":"雙鴻科技","action":"FULL_SELL","weight_before":0.74,"weight_after":0.0,"weight_change":-0.74,"shares_change":-299000.0,"close_price":1060.0,"amount_change":-316940000.0},{"trade_date":"2026-05-12","etf_code":"00991A","stock_code":"6669","stock_name":"緯穎科技","action":"INCREASE","weight_before":3.31,"weight_after":3.8,"weight_change":0.49,"shares_change":20000.0,"close_price":5340.0,"amount_change":106800000.0},{"trade_date":"2026-05-12","etf_code":"00991A","stock_code":"8299","stock_name":"群聯電子","action":"INCREASE","weight_before":8.16,"weight_after":8.4,"weight_change":0.24,"shares_change":30000.0,"close_price":2725.0,"amount_change":81750000.0},{"trade_date":"2026-05-12","etf_code":"00991A","stock_code":"8996","stock_name":"高力熱處","action":"INCREASE","weight_before":0.8,"weight_after":1.41,"weight_change":0.61,"shares_change":260000.0,"close_price":1055.0,"amount_change":274300000.0},{"trade_date":"2026-05-12","etf_code":"00992A","stock_code":"2059","stock_name":"川湖","action":"INCREASE","weight_before":2.69,"weight_after":3.66,"weight_change":0.97,"shares_change":100000.0,"close_price":5520.0,"amount_change":552000000.0},{"trade_date":"2026-05-12","etf_code":"00992A","stock_code":"7751","stock_name":"竑騰","action":"INCREASE","weight_before":1.28,"weight_after":1.33,"weight_change":0.05,"shares_change":-1000.0,"close_price":1835.0,"amount_change":-1835000.0},{"trade_date":"2026-05-12","etf_code":"00992A","stock_code":"8046","stock_name":"南電","action":"INCREASE","weight_before":1.9,"weight_after":2.8,"weight_change":0.9,"shares_change":550000.0,"close_price":908.0,"amount_change":499400000.0},{"trade_date":"2026-05-12","etf_code":"00993A","stock_code":"1303","stock_name":"南亞","action":"DECREASE","weight_before":1.06,"weight_after":0.75,"weight_change":-0.31,"shares_change":-403000.0,"close_price":91.5,"amount_change":-36874500.0},{"trade_date":"2026-05-12","etf_code":"00993A","stock_code":"1560","stock_name":"中砂","action":"FULL_SELL","weight_before":1.08,"weight_after":0.0,"weight_change":-1.08,"shares_change":-212000.0,"close_price":629.0,"amount_change":-133348000.0},{"trade_date":"2026-05-12","etf_code":"00993A","stock_code":"1590","stock_name":"亞德客-KY","action":"DECREASE","weight_before":1.05,"weight_after":0.79,"weight_change":-0.26,"shares_change":-21000.0,"close_price":1550.0,"amount_change":-32550000.0},{"trade_date":"2026-05-12","etf_code":"00993A","stock_code":"1815","stock_name":"富喬工業","action":"DECREASE","weight_before":1.0,"weight_after":0.71,"weight_change":-0.29,"shares_change":-323000.0,"close_price":108.0,"amount_change":-34884000.0},{"trade_date":"2026-05-12","etf_code":"00993A","stock_code":"2027","stock_name":"大成鋼","action":"FULL_SELL","weight_before":1.07,"weight_after":0.0,"weight_change":-1.07,"shares_change":-3305000.0,"close_price":39.95,"amount_change":-132034750.0},{"trade_date":"2026-05-12","etf_code":"00993A","stock_code":"2049","stock_name":"上銀科技","action":"DECREASE","weight_before":1.15,"weight_after":0.93,"weight_change":-0.22,"shares_change":-100000.0,"close_price":351.0,"amount_change":-35100000.0},{"trade_date":"2026-05-12","etf_code":"00993A","stock_code":"2308","stock_name":"台達電子","action":"INCREASE","weight_before":1.06,"weight_after":2.76,"weight_change":1.7,"shares_change":93000.0,"close_price":2245.0,"amount_change":208785000.0},{"trade_date":"2026-05-12","etf_code":"00993A","stock_code":"2313","stock_name":"華通","action":"DECREASE","weight_before":1.01,"weight_after":0.81,"weight_change":-0.2,"shares_change":-141000.0,"close_price":242.0,"amount_change":-34122000.0},{"trade_date":"2026-05-12","etf_code":"00993A","stock_code":"2327","stock_name":"國巨*","action":"DECREASE","weight_before":1.21,"weight_after":1.04,"weight_change":-0.17,"shares_change":-81000.0,"close_price":391.5,"amount_change":-31711500.0},{"trade_date":"2026-05-12","etf_code":"00993A","stock_code":"2330","stock_name":"台積電","action":"INCREASE","weight_before":7.34,"weight_after":8.27,"weight_change":0.93,"shares_change":37000.0,"close_price":2235.0,"amount_change":82695000.0},{"trade_date":"2026-05-12","etf_code":"00993A","stock_code":"2337","stock_name":"旺宏","action":"FULL_SELL","weight_before":8.94,"weight_after":0.0,"weight_change":-8.94,"shares_change":-6898000.0,"close_price":159.5,"amount_change":-1100231000.0},{"trade_date":"2026-05-12","etf_code":"00993A","stock_code":"2344","stock_name":"華邦電子","action":"NEW_BUY","weight_before":0.0,"weight_after":1.14,"weight_change":1.14,"shares_change":1124000.0,"close_price":117.5,"amount_change":132070000.0},{"trade_date":"2026-05-12","etf_code":"00993A","stock_code":"2345","stock_name":"智邦","action":"INCREASE","weight_before":1.12,"weight_after":2.8,"weight_change":1.68,"shares_change":80000.0,"close_price":2590.0,"amount_change":207200000.0},{"trade_date":"2026-05-12","etf_code":"00993A","stock_code":"2360","stock_name":"致茂","action":"INCREASE","weight_before":1.13,"weight_after":1.61,"weight_change":0.48,"shares_change":20000.0,"close_price":2360.0,"amount_change":47200000.0},{"trade_date":"2026-05-12","etf_code":"00993A","stock_code":"2368","stock_name":"金像電子","action":"INCREASE","weight_before":0.95,"weight_after":1.98,"weight_change":1.03,"shares_change":88000.0,"close_price":1400.0,"amount_change":123200000.0},{"trade_date":"2026-05-12","etf_code":"00993A","stock_code":"2383","stock_name":"台光電子","action":"INCREASE","weight_before":4.46,"weight_after":5.43,"weight_change":0.97,"shares_change":20000.0,"close_price":4850.0,"amount_change":97000000.0},{"trade_date":"2026-05-12","etf_code":"00993A","stock_code":"2404","stock_name":"漢唐","action":"FULL_SELL","weight_before":0.98,"weight_after":0.0,"weight_change":-0.98,"shares_change":-117000.0,"close_price":1025.0,"amount_change":-119925000.0},{"trade_date":"2026-05-12","etf_code":"00993A","stock_code":"2408","stock_name":"南亞科","action":"NEW_BUY","weight_before":0.0,"weight_after":0.18,"weight_change":0.18,"shares_change":66000.0,"close_price":301.0,"amount_change":19866000.0},{"trade_date":"2026-05-12","etf_code":"00993A","stock_code":"2606","stock_name":"裕民","action":"FULL_SELL","weight_before":1.02,"weight_after":0.0,"weight_change":-1.02,"shares_change":-1925000.0,"close_price":65.3,"amount_change":-125702500.0},{"trade_date":"2026-05-12","etf_code":"00993A","stock_code":"2610","stock_name":"華航","action":"FULL_SELL","weight_before":1.05,"weight_after":0.0,"weight_change":-1.05,"shares_change":-6729000.0,"close_price":19.15,"amount_change":-128860350.0},{"trade_date":"2026-05-12","etf_code":"00993A","stock_code":"2618","stock_name":"長榮航","action":"FULL_SELL","weight_before":1.03,"weight_after":0.0,"weight_change":-1.03,"shares_change":-3523000.0,"close_price":35.85,"amount_change":-126299550.0},{"trade_date":"2026-05-12","etf_code":"00993A","stock_code":"2883","stock_name":"凱基金控","action":"DECREASE","weight_before":1.24,"weight_after":0.94,"weight_change":-0.3,"shares_change":-1443000.0,"close_price":22.8,"amount_change":-32900400.0},{"trade_date":"2026-05-12","etf_code":"00993A","stock_code":"3017","stock_name":"奇鋐","action":"INCREASE","weight_before":0.81,"weight_after":2.27,"weight_change":1.46,"shares_change":69000.0,"close_price":2555.0,"amount_change":176295000.0},{"trade_date":"2026-05-12","etf_code":"00993A","stock_code":"3036","stock_name":"文曄","action":"DECREASE","weight_before":1.26,"weight_after":1.0,"weight_change":-0.26,"shares_change":-151000.0,"close_price":264.5,"amount_change":-39939500.0},{"trade_date":"2026-05-12","etf_code":"00993A","stock_code":"3037","stock_name":"欣興","action":"INCREASE","weight_before":1.62,"weight_after":2.6,"weight_change":0.98,"shares_change":125000.0,"close_price":861.0,"amount_change":107625000.0},{"trade_date":"2026-05-12","etf_code":"00993A","stock_code":"3044","stock_name":"健鼎科技","action":"DECREASE","weight_before":0.97,"weight_after":0.77,"weight_change":-0.2,"shares_change":-52000.0,"close_price":489.5,"amount_change":-25454000.0},{"trade_date":"2026-05-12","etf_code":"00993A","stock_code":"3105","stock_name":"穩懋","action":"DECREASE","weight_before":4.55,"weight_after":2.86,"weight_change":-1.69,"shares_change":-393000.0,"close_price":512.0,"amount_change":-201216000.0},{"trade_date":"2026-05-12","etf_code":"00993A","stock_code":"3189","stock_name":"景碩科技","action":"DECREASE","weight_before":7.36,"weight_after":4.62,"weight_change":-2.74,"shares_change":-678000.0,"close_price":503.0,"amount_change":-341034000.0},{"trade_date":"2026-05-12","etf_code":"00993A","stock_code":"3260","stock_name":"威剛科技","action":"FULL_SELL","weight_before":1.1,"weight_after":0.0,"weight_change":-1.1,"shares_change":-296000.0,"close_price":445.5,"amount_change":-131868000.0},{"trade_date":"2026-05-12","etf_code":"00993A","stock_code":"3264","stock_name":"欣銓","action":"INCREASE","weight_before":0.95,"weight_after":1.52,"weight_change":0.57,"shares_change":277000.0,"close_price":228.5,"amount_change":63294500.0},{"trade_date":"2026-05-12","etf_code":"00993A","stock_code":"3443","stock_name":"創意電子","action":"NEW_BUY","weight_before":0.0,"weight_after":3.02,"weight_change":3.02,"shares_change":65000.0,"close_price":5730.0,"amount_change":372450000.0},{"trade_date":"2026-05-12","etf_code":"00993A","stock_code":"3491","stock_name":"昇達科技","action":"DECREASE","weight_before":1.01,"weight_after":0.76,"weight_change":-0.25,"shares_change":-16000.0,"close_price":1765.0,"amount_change":-28240000.0},{"trade_date":"2026-05-12","etf_code":"00993A","stock_code":"3533","stock_name":"嘉澤端子","action":"DECREASE","weight_before":1.09,"weight_after":0.82,"weight_change":-0.27,"shares_change":-12000.0,"close_price":2845.0,"amount_change":-34140000.0},{"trade_date":"2026-05-12","etf_code":"00993A","stock_code":"3653","stock_name":"健策","action":"NEW_BUY","weight_before":0.0,"weight_after":1.01,"weight_change":1.01,"shares_change":31000.0,"close_price":4015.0,"amount_change":124465000.0},{"trade_date":"2026-05-12","etf_code":"00993A","stock_code":"3661","stock_name":"世芯-KY","action":"NEW_BUY","weight_before":0.0,"weight_after":0.18,"weight_change":0.18,"shares_change":4000.0,"close_price":5375.0,"amount_change":21500000.0},{"trade_date":"2026-05-12","etf_code":"00993A","stock_code":"3665","stock_name":"貿聯-KY","action":"INCREASE","weight_before":0.99,"weight_after":2.43,"weight_change":1.44,"shares_change":63000.0,"close_price":2905.0,"amount_change":183015000.0},{"trade_date":"2026-05-12","etf_code":"00993A","stock_code":"3680","stock_name":"家登精密","action":"NEW_BUY","weight_before":0.0,"weight_after":0.17,"weight_change":0.17,"shares_change":34000.0,"close_price":602.0,"amount_change":20468000.0},{"trade_date":"2026-05-12","etf_code":"00993A","stock_code":"3702","stock_name":"大聯大","action":"DECREASE","weight_before":5.63,"weight_after":4.12,"weight_change":-1.51,"shares_change":-1731000.0,"close_price":114.0,"amount_change":-197334000.0},{"trade_date":"2026-05-12","etf_code":"00993A","stock_code":"4749","stock_name":"新應材","action":"DECREASE","weight_before":1.18,"weight_after":0.94,"weight_change":-0.24,"shares_change":-27000.0,"close_price":1175.0,"amount_change":-31725000.0},{"trade_date":"2026-05-12","etf_code":"00993A","stock_code":"4958","stock_name":"臻鼎-KY","action":"DECREASE","weight_before":1.04,"weight_after":0.9,"weight_change":-0.14,"shares_change":-44000.0,"close_price":412.0,"amount_change":-18128000.0},{"trade_date":"2026-05-12","etf_code":"00993A","stock_code":"5234","stock_name":"達興材料","action":"FULL_SELL","weight_before":0.96,"weight_after":0.0,"weight_change":-0.96,"shares_change":-286000.0,"close_price":414.5,"amount_change":-118547000.0},{"trade_date":"2026-05-12","etf_code":"00993A","stock_code":"5274","stock_name":"信驊科技","action":"INCREASE","weight_before":1.01,"weight_after":3.45,"weight_change":2.44,"shares_change":16000.0,"close_price":18005.0,"amount_change":288080000.0},{"trade_date":"2026-05-12","etf_code":"00993A","stock_code":"5289","stock_name":"宜鼎國際","action":"DECREASE","weight_before":1.52,"weight_after":1.21,"weight_change":-0.31,"shares_change":-25000.0,"close_price":1795.0,"amount_change":-44875000.0},{"trade_date":"2026-05-12","etf_code":"00993A","stock_code":"6213","stock_name":"聯茂","action":"DECREASE","weight_before":1.79,"weight_after":1.28,"weight_change":-0.51,"shares_change":-195000.0,"close_price":300.5,"amount_change":-58597500.0},{"trade_date":"2026-05-12","etf_code":"00993A","stock_code":"6285","stock_name":"啟碁科技","action":"DECREASE","weight_before":1.17,"weight_after":0.91,"weight_change":-0.26,"shares_change":-166000.0,"close_price":259.0,"amount_change":-42994000.0},{"trade_date":"2026-05-12","etf_code":"00993A","stock_code":"6415","stock_name":"矽力*-KY","action":"NEW_BUY","weight_before":0.0,"weight_after":0.2,"weight_change":0.2,"shares_change":50000.0,"close_price":468.0,"amount_change":23400000.0},{"trade_date":"2026-05-12","etf_code":"00993A","stock_code":"6515","stock_name":"穎崴","action":"INCREASE","weight_before":7.3,"weight_after":7.55,"weight_change":0.25,"shares_change":2000.0,"close_price":10090.0,"amount_change":20180000.0},{"trade_date":"2026-05-12","etf_code":"00993A","stock_code":"6584","stock_name":"南俊國際","action":"DECREASE","weight_before":2.92,"weight_after":1.89,"weight_change":-1.03,"shares_change":-190000.0,"close_price":681.0,"amount_change":-129390000.0},{"trade_date":"2026-05-12","etf_code":"00993A","stock_code":"6640","stock_name":"均華","action":"NEW_BUY","weight_before":0.0,"weight_after":0.16,"weight_change":0.16,"shares_change":13000.0,"close_price":1475.0,"amount_change":19175000.0},{"trade_date":"2026-05-12","etf_code":"00993A","stock_code":"6669","stock_name":"緯穎","action":"INCREASE","weight_before":1.09,"weight_after":2.17,"weight_change":1.08,"shares_change":20000.0,"close_price":5340.0,"amount_change":106800000.0},{"trade_date":"2026-05-12","etf_code":"00993A","stock_code":"6805","stock_name":"富世達","action":"DECREASE","weight_before":0.96,"weight_after":0.68,"weight_change":-0.28,"shares_change":-15000.0,"close_price":1995.0,"amount_change":-29925000.0},{"trade_date":"2026-05-12","etf_code":"00993A","stock_code":"7769","stock_name":"鴻勁","action":"DECREASE","weight_before":1.19,"weight_after":1.09,"weight_change":-0.1,"shares_change":-4000.0,"close_price":6380.0,"amount_change":-25520000.0},{"trade_date":"2026-05-12","etf_code":"00993A","stock_code":"8021","stock_name":"尖點","action":"NEW_BUY","weight_before":0.0,"weight_after":0.08,"weight_change":0.08,"shares_change":21000.0,"close_price":429.0,"amount_change":9009000.0},{"trade_date":"2026-05-12","etf_code":"00993A","stock_code":"8046","stock_name":"南電","action":"INCREASE","weight_before":1.03,"weight_after":1.58,"weight_change":0.55,"shares_change":71000.0,"close_price":908.0,"amount_change":64468000.0},{"trade_date":"2026-05-12","etf_code":"00993A","stock_code":"8210","stock_name":"勤誠興業","action":"DECREASE","weight_before":1.24,"weight_after":1.05,"weight_change":-0.19,"shares_change":-17000.0,"close_price":1555.0,"amount_change":-26435000.0},{"trade_date":"2026-05-12","etf_code":"00993A","stock_code":"8299","stock_name":"群聯電子","action":"NEW_BUY","weight_before":0.0,"weight_after":0.25,"weight_change":0.25,"shares_change":11000.0,"close_price":2725.0,"amount_change":29975000.0},{"trade_date":"2026-05-12","etf_code":"00994A","stock_code":"2303","stock_name":"聯電","action":"INCREASE","weight_before":0.85,"weight_after":1.38,"weight_change":0.53,"shares_change":250000.0,"close_price":95.0,"amount_change":23750000.0},{"trade_date":"2026-05-12","etf_code":"00994A","stock_code":"2327","stock_name":"國巨*","action":"INCREASE","weight_before":0.47,"weight_after":1.01,"weight_change":0.54,"shares_change":70000.0,"close_price":391.5,"amount_change":27405000.0},{"trade_date":"2026-05-12","etf_code":"00994A","stock_code":"2330","stock_name":"台積電","action":"DECREASE","weight_before":16.13,"weight_after":13.85,"weight_change":-2.28,"shares_change":-60000.0,"close_price":2235.0,"amount_change":-134100000.0},{"trade_date":"2026-05-12","etf_code":"00994A","stock_code":"3036","stock_name":"文曄","action":"NEW_BUY","weight_before":0.0,"weight_after":0.28,"weight_change":0.28,"shares_change":60000.0,"close_price":264.5,"amount_change":15870000.0},{"trade_date":"2026-05-12","etf_code":"00994A","stock_code":"3081","stock_name":"聯亞","action":"INCREASE","weight_before":0.82,"weight_after":1.42,"weight_change":0.6,"shares_change":10000.0,"close_price":3055.0,"amount_change":30550000.0},{"trade_date":"2026-05-12","etf_code":"00994A","stock_code":"6669","stock_name":"緯穎","action":"INCREASE","weight_before":3.04,"weight_after":4.08,"weight_change":1.04,"shares_change":8000.0,"close_price":5340.0,"amount_change":42720000.0},{"trade_date":"2026-05-12","etf_code":"00994A","stock_code":"7769","stock_name":"鴻勁","action":"INCREASE","weight_before":2.31,"weight_after":3.07,"weight_change":0.76,"shares_change":5000.0,"close_price":6380.0,"amount_change":31900000.0},{"trade_date":"2026-05-12","etf_code":"00999A","stock_code":"1477","stock_name":"聚陽實業","action":"INCREASE","weight_before":2.61,"weight_after":2.73,"weight_change":0.12,"shares_change":34000.0,"close_price":218.0,"amount_change":7412000.0},{"trade_date":"2026-05-12","etf_code":"00999A","stock_code":"2330","stock_name":"台灣積體電路製造","action":"INCREASE","weight_before":7.3,"weight_after":7.35,"weight_change":0.05,"shares_change":9000.0,"close_price":2235.0,"amount_change":20115000.0},{"trade_date":"2026-05-12","etf_code":"00999A","stock_code":"2357","stock_name":"華碩電腦","action":"DECREASE","weight_before":3.05,"weight_after":2.98,"weight_change":-0.07,"shares_change":13000.0,"close_price":686.0,"amount_change":8918000.0},{"trade_date":"2026-05-12","etf_code":"00999A","stock_code":"2360","stock_name":"致茂電子","action":"INCREASE","weight_before":1.91,"weight_after":1.97,"weight_change":0.06,"shares_change":2000.0,"close_price":2360.0,"amount_change":4720000.0},{"trade_date":"2026-05-12","etf_code":"00999A","stock_code":"2408","stock_name":"南亞科技","action":"INCREASE","weight_before":1.68,"weight_after":1.79,"weight_change":0.11,"shares_change":16000.0,"close_price":301.0,"amount_change":4816000.0},{"trade_date":"2026-05-12","etf_code":"00999A","stock_code":"2548","stock_name":"華固建設","action":"DECREASE","weight_before":1.64,"weight_after":1.56,"weight_change":-0.08,"shares_change":36000.0,"close_price":129.5,"amount_change":4662000.0},{"trade_date":"2026-05-12","etf_code":"00999A","stock_code":"2618","stock_name":"長榮航空","action":"DECREASE","weight_before":2.29,"weight_after":2.24,"weight_change":-0.05,"shares_change":180000.0,"close_price":35.85,"amount_change":6453000.0},{"trade_date":"2026-05-12","etf_code":"00999A","stock_code":"3711","stock_name":"日月光投資控股","action":"INCREASE","weight_before":1.57,"weight_after":1.62,"weight_change":0.05,"shares_change":8000.0,"close_price":537.0,"amount_change":4296000.0},{"trade_date":"2026-05-12","etf_code":"00999A","stock_code":"6121","stock_name":"新普科技","action":"DECREASE","weight_before":1.64,"weight_after":1.59,"weight_change":-0.05,"shares_change":12000.0,"close_price":382.0,"amount_change":4584000.0},{"trade_date":"2026-05-12","etf_code":"00999A","stock_code":"6669","stock_name":"緯穎科技服務","action":"INCREASE","weight_before":2.61,"weight_after":2.81,"weight_change":0.2,"shares_change":1000.0,"close_price":5340.0,"amount_change":5340000.0},{"trade_date":"2026-05-12","etf_code":"00999A","stock_code":"7769","stock_name":"鴻勁精密","action":"INCREASE","weight_before":2.74,"weight_after":2.93,"weight_change":0.19,"shares_change":1000.0,"close_price":6380.0,"amount_change":6380000.0}]