[{"trade_date":"2026-07-23","etf_code":"00400A","stock_code":"2368","stock_name":"金像電","action":"FULL_SELL","weight_before":0.98,"weight_after":0.0,"weight_change":-0.98,"shares_change":-260000.0,"close_price":940.0,"amount_change":-244400000.0},{"trade_date":"2026-07-23","etf_code":"00400A","stock_code":"2481","stock_name":"強  茂","action":"FULL_SELL","weight_before":0.31,"weight_after":0.0,"weight_change":-0.31,"shares_change":-565000.0,"close_price":157.5,"amount_change":-88987500.0},{"trade_date":"2026-07-23","etf_code":"00400A","stock_code":"3008","stock_name":"大立光","action":"NEW_BUY","weight_before":0.0,"weight_after":0.94,"weight_change":0.94,"shares_change":61000.0,"close_price":4000.0,"amount_change":244000000.0},{"trade_date":"2026-07-23","etf_code":"00400A","stock_code":"3037","stock_name":"欣興","action":"INCREASE","weight_before":3.97,"weight_after":4.43,"weight_change":0.46,"shares_change":86000.0,"close_price":907.0,"amount_change":78002000.0},{"trade_date":"2026-07-23","etf_code":"00400A","stock_code":"5274","stock_name":"信  驊","action":"INCREASE","weight_before":2.52,"weight_after":3.02,"weight_change":0.5,"shares_change":6000.0,"close_price":15540.0,"amount_change":93240000.0},{"trade_date":"2026-07-23","etf_code":"00400A","stock_code":"6187","stock_name":"萬  潤","action":"INCREASE","weight_before":1.34,"weight_after":2.26,"weight_change":0.92,"shares_change":247000.0,"close_price":1025.0,"amount_change":253175000.0},{"trade_date":"2026-07-23","etf_code":"00400A","stock_code":"6442","stock_name":"光  聖","action":"INCREASE","weight_before":0.37,"weight_after":0.58,"weight_change":0.21,"shares_change":35000.0,"close_price":1385.0,"amount_change":48475000.0},{"trade_date":"2026-07-23","etf_code":"00400A","stock_code":"8210","stock_name":"勤  誠","action":"FULL_SELL","weight_before":1.12,"weight_after":0.0,"weight_change":-1.12,"shares_change":-250000.0,"close_price":1150.0,"amount_change":-287500000.0},{"trade_date":"2026-07-23","etf_code":"00403A","stock_code":"1303","stock_name":"南亞","action":"INCREASE","weight_before":1.18,"weight_after":1.25,"weight_change":0.07,"shares_change":800000.0,"close_price":208.0,"amount_change":166400000.0},{"trade_date":"2026-07-23","etf_code":"00403A","stock_code":"2303","stock_name":"聯電","action":"INCREASE","weight_before":6.14,"weight_after":6.24,"weight_change":0.1,"shares_change":1000000.0,"close_price":139.0,"amount_change":139000000.0},{"trade_date":"2026-07-23","etf_code":"00403A","stock_code":"2308","stock_name":"台達電","action":"INCREASE","weight_before":3.15,"weight_after":3.39,"weight_change":0.24,"shares_change":220000.0,"close_price":1880.0,"amount_change":413600000.0},{"trade_date":"2026-07-23","etf_code":"00403A","stock_code":"2330","stock_name":"台積電","action":"DECREASE","weight_before":18.78,"weight_after":16.55,"weight_change":-2.23,"shares_change":-1200000.0,"close_price":2400.0,"amount_change":-2880000000.0},{"trade_date":"2026-07-23","etf_code":"00403A","stock_code":"2345","stock_name":"智邦","action":"INCREASE","weight_before":2.97,"weight_after":3.12,"weight_change":0.15,"shares_change":60000.0,"close_price":2285.0,"amount_change":137100000.0},{"trade_date":"2026-07-23","etf_code":"00403A","stock_code":"2360","stock_name":"致茂","action":"INCREASE","weight_before":0.83,"weight_after":0.97,"weight_change":0.14,"shares_change":80000.0,"close_price":2125.0,"amount_change":170000000.0},{"trade_date":"2026-07-23","etf_code":"00403A","stock_code":"2383","stock_name":"台光電","action":"INCREASE","weight_before":3.7,"weight_after":4.02,"weight_change":0.32,"shares_change":70000.0,"close_price":5125.0,"amount_change":358750000.0},{"trade_date":"2026-07-23","etf_code":"00403A","stock_code":"2454","stock_name":"聯發科","action":"INCREASE","weight_before":3.75,"weight_after":3.98,"weight_change":0.23,"shares_change":50000.0,"close_price":3850.0,"amount_change":192500000.0},{"trade_date":"2026-07-23","etf_code":"00403A","stock_code":"3037","stock_name":"欣興","action":"INCREASE","weight_before":3.59,"weight_after":4.04,"weight_change":0.45,"shares_change":458000.0,"close_price":907.0,"amount_change":415406000.0},{"trade_date":"2026-07-23","etf_code":"00403A","stock_code":"3443","stock_name":"創意","action":"INCREASE","weight_before":1.2,"weight_after":1.32,"weight_change":0.12,"shares_change":30000.0,"close_price":4370.0,"amount_change":131100000.0},{"trade_date":"2026-07-23","etf_code":"00403A","stock_code":"3653","stock_name":"健策","action":"INCREASE","weight_before":1.87,"weight_after":2.05,"weight_change":0.18,"shares_change":57000.0,"close_price":3500.0,"amount_change":199500000.0},{"trade_date":"2026-07-23","etf_code":"00403A","stock_code":"3665","stock_name":"貿聯-KY","action":"INCREASE","weight_before":0.46,"weight_after":0.81,"weight_change":0.35,"shares_change":224000.0,"close_price":2115.0,"amount_change":473760000.0},{"trade_date":"2026-07-23","etf_code":"00403A","stock_code":"4958","stock_name":"臻鼎-KY","action":"DECREASE","weight_before":2.15,"weight_after":1.85,"weight_change":-0.3,"shares_change":-780000.0,"close_price":559.0,"amount_change":-436020000.0},{"trade_date":"2026-07-23","etf_code":"00403A","stock_code":"5274","stock_name":"信驊","action":"INCREASE","weight_before":0.94,"weight_after":1.15,"weight_change":0.21,"shares_change":15000.0,"close_price":15540.0,"amount_change":233100000.0},{"trade_date":"2026-07-23","etf_code":"00403A","stock_code":"6239","stock_name":"力成","action":"INCREASE","weight_before":0.23,"weight_after":0.41,"weight_change":0.18,"shares_change":950000.0,"close_price":294.0,"amount_change":279300000.0},{"trade_date":"2026-07-23","etf_code":"00403A","stock_code":"6669","stock_name":"緯穎","action":"DECREASE","weight_before":2.4,"weight_after":1.95,"weight_change":-0.45,"shares_change":-190000.0,"close_price":5500.0,"amount_change":-1045000000.0},{"trade_date":"2026-07-23","etf_code":"00403A","stock_code":"6805","stock_name":"富世達","action":"INCREASE","weight_before":0.53,"weight_after":0.6,"weight_change":0.07,"shares_change":80000.0,"close_price":1395.0,"amount_change":111600000.0},{"trade_date":"2026-07-23","etf_code":"00405A","stock_code":"2337","stock_name":"旺宏","action":"FULL_SELL","weight_before":1.38,"weight_after":0.0,"weight_change":-1.38,"shares_change":-2800000.0,"close_price":135.0,"amount_change":-378000000.0},{"trade_date":"2026-07-23","etf_code":"00405A","stock_code":"3665","stock_name":"貿聯-KY","action":"INCREASE","weight_before":0.89,"weight_after":4.13,"weight_change":3.24,"shares_change":380000.0,"close_price":2115.0,"amount_change":803700000.0},{"trade_date":"2026-07-23","etf_code":"00405A","stock_code":"6274","stock_name":"台燿","action":"INCREASE","weight_before":1.42,"weight_after":1.49,"weight_change":0.07,"shares_change":20000.0,"close_price":1335.0,"amount_change":26700000.0},{"trade_date":"2026-07-23","etf_code":"00980A","stock_code":"1303","stock_name":"南亞塑膠工業","action":"INCREASE","weight_before":0.96,"weight_after":1.46,"weight_change":0.5,"shares_change":461000.0,"close_price":208.0,"amount_change":95888000.0},{"trade_date":"2026-07-23","etf_code":"00980A","stock_code":"2059","stock_name":"川湖科技","action":"DECREASE","weight_before":5.49,"weight_after":4.56,"weight_change":-0.93,"shares_change":-19000.0,"close_price":8125.0,"amount_change":-154375000.0},{"trade_date":"2026-07-23","etf_code":"00980A","stock_code":"2376","stock_name":"技嘉科技","action":"INCREASE","weight_before":1.18,"weight_after":1.35,"weight_change":0.17,"shares_change":70000.0,"close_price":348.0,"amount_change":24360000.0},{"trade_date":"2026-07-23","etf_code":"00980A","stock_code":"2408","stock_name":"南亞科技","action":"INCREASE","weight_before":1.88,"weight_after":2.31,"weight_change":0.43,"shares_change":204000.0,"close_price":445.5,"amount_change":90882000.0},{"trade_date":"2026-07-23","etf_code":"00980A","stock_code":"3189","stock_name":"景碩科技","action":"INCREASE","weight_before":0.68,"weight_after":0.88,"weight_change":0.2,"shares_change":45000.0,"close_price":796.0,"amount_change":35820000.0},{"trade_date":"2026-07-23","etf_code":"00980A","stock_code":"3231","stock_name":"緯創資通","action":"INCREASE","weight_before":0.71,"weight_after":0.92,"weight_change":0.21,"shares_change":171000.0,"close_price":164.0,"amount_change":28044000.0},{"trade_date":"2026-07-23","etf_code":"00980A","stock_code":"3293","stock_name":"鈊象電子","action":"INCREASE","weight_before":0.83,"weight_after":0.98,"weight_change":0.15,"shares_change":37000.0,"close_price":713.0,"amount_change":26381000.0},{"trade_date":"2026-07-23","etf_code":"00980A","stock_code":"3443","stock_name":"創意電子","action":"DECREASE","weight_before":1.88,"weight_after":1.58,"weight_change":-0.3,"shares_change":-11000.0,"close_price":4370.0,"amount_change":-48070000.0},{"trade_date":"2026-07-23","etf_code":"00980A","stock_code":"5274","stock_name":"信驊科技","action":"INCREASE","weight_before":1.36,"weight_after":1.55,"weight_change":0.19,"shares_change":2000.0,"close_price":15540.0,"amount_change":31080000.0},{"trade_date":"2026-07-23","etf_code":"00980A","stock_code":"6213","stock_name":"聯茂電子","action":"INCREASE","weight_before":0.42,"weight_after":0.68,"weight_change":0.26,"shares_change":136000.0,"close_price":367.0,"amount_change":49912000.0},{"trade_date":"2026-07-23","etf_code":"00980A","stock_code":"6274","stock_name":"台燿科技","action":"INCREASE","weight_before":1.08,"weight_after":1.34,"weight_change":0.26,"shares_change":34000.0,"close_price":1335.0,"amount_change":45390000.0},{"trade_date":"2026-07-23","etf_code":"00980A","stock_code":"6669","stock_name":"緯穎科技服務","action":"INCREASE","weight_before":1.42,"weight_after":1.57,"weight_change":0.15,"shares_change":5000.0,"close_price":5500.0,"amount_change":27500000.0},{"trade_date":"2026-07-23","etf_code":"00980A","stock_code":"7769","stock_name":"鴻勁精密","action":"DECREASE","weight_before":3.15,"weight_after":2.88,"weight_change":-0.27,"shares_change":-7000.0,"close_price":6405.0,"amount_change":-44835000.0},{"trade_date":"2026-07-23","etf_code":"00980A","stock_code":"8046","stock_name":"南亞電路板","action":"DECREASE","weight_before":1.76,"weight_after":1.53,"weight_change":-0.23,"shares_change":-16000.0,"close_price":1305.0,"amount_change":-20880000.0},{"trade_date":"2026-07-23","etf_code":"00980A","stock_code":"8996","stock_name":"高力熱處理工業","action":"DECREASE","weight_before":1.47,"weight_after":1.19,"weight_change":-0.28,"shares_change":-40000.0,"close_price":1080.0,"amount_change":-43200000.0},{"trade_date":"2026-07-23","etf_code":"00981A","stock_code":"2368","stock_name":"金像電","action":"DECREASE","weight_before":2.81,"weight_after":2.51,"weight_change":-0.3,"shares_change":-837000.0,"close_price":940.0,"amount_change":-786780000.0},{"trade_date":"2026-07-23","etf_code":"00981A","stock_code":"6147","stock_name":"頎邦","action":"DECREASE","weight_before":0.36,"weight_after":0.3,"weight_change":-0.06,"shares_change":-523000.0,"close_price":175.5,"amount_change":-91786500.0},{"trade_date":"2026-07-23","etf_code":"00981A","stock_code":"6805","stock_name":"富世達","action":"INCREASE","weight_before":0.94,"weight_after":1.0,"weight_change":0.06,"shares_change":50000.0,"close_price":1395.0,"amount_change":69750000.0},{"trade_date":"2026-07-23","etf_code":"00982A","stock_code":"6147","stock_name":"頎邦","action":"DECREASE","weight_before":0.91,"weight_after":0.42,"weight_change":-0.49,"shares_change":-1200000.0,"close_price":175.5,"amount_change":-210600000.0},{"trade_date":"2026-07-23","etf_code":"00984A","stock_code":"1216","stock_name":"統一","action":"DECREASE","weight_before":2.02,"weight_after":1.92,"weight_change":-0.1,"shares_change":31000.0,"close_price":76.8,"amount_change":2380800.0},{"trade_date":"2026-07-23","etf_code":"00984A","stock_code":"2303","stock_name":"聯電","action":"INCREASE","weight_before":1.93,"weight_after":2.28,"weight_change":0.35,"shares_change":234000.0,"close_price":139.0,"amount_change":32526000.0},{"trade_date":"2026-07-23","etf_code":"00984A","stock_code":"2357","stock_name":"華碩","action":"INCREASE","weight_before":2.77,"weight_after":2.82,"weight_change":0.05,"shares_change":5000.0,"close_price":757.0,"amount_change":3785000.0},{"trade_date":"2026-07-23","etf_code":"00984A","stock_code":"2377","stock_name":"微星","action":"INCREASE","weight_before":0.97,"weight_after":1.02,"weight_change":0.05,"shares_change":8000.0,"close_price":155.0,"amount_change":1240000.0},{"trade_date":"2026-07-23","etf_code":"00984A","stock_code":"2382","stock_name":"廣達","action":"INCREASE","weight_before":2.15,"weight_after":2.26,"weight_change":0.11,"shares_change":37000.0,"close_price":329.0,"amount_change":12173000.0},{"trade_date":"2026-07-23","etf_code":"00984A","stock_code":"2404","stock_name":"漢唐","action":"INCREASE","weight_before":1.77,"weight_after":1.85,"weight_change":0.08,"shares_change":7000.0,"close_price":1175.0,"amount_change":8225000.0},{"trade_date":"2026-07-23","etf_code":"00984A","stock_code":"2634","stock_name":"漢翔公司","action":"DECREASE","weight_before":0.5,"weight_after":0.44,"weight_change":-0.06,"shares_change":8000.0,"close_price":64.4,"amount_change":515200.0},{"trade_date":"2026-07-23","etf_code":"00984A","stock_code":"3034","stock_name":"聯詠","action":"INCREASE","weight_before":1.94,"weight_after":2.01,"weight_change":0.07,"shares_change":4000.0,"close_price":501.0,"amount_change":2004000.0},{"trade_date":"2026-07-23","etf_code":"00984A","stock_code":"3189","stock_name":"景碩科技","action":"INCREASE","weight_before":1.06,"weight_after":1.35,"weight_change":0.29,"shares_change":29000.0,"close_price":796.0,"amount_change":23084000.0},{"trade_date":"2026-07-23","etf_code":"00984A","stock_code":"3532","stock_name":"台勝科","action":"INCREASE","weight_before":0.69,"weight_after":0.74,"weight_change":0.05,"shares_change":3000.0,"close_price":468.0,"amount_change":1404000.0},{"trade_date":"2026-07-23","etf_code":"00984A","stock_code":"5434","stock_name":"崇越","action":"INCREASE","weight_before":1.15,"weight_after":1.2,"weight_change":0.05,"shares_change":7000.0,"close_price":565.0,"amount_change":3955000.0},{"trade_date":"2026-07-23","etf_code":"00984A","stock_code":"6223","stock_name":"旺矽","action":"INCREASE","weight_before":1.05,"weight_after":1.11,"weight_change":0.06,"shares_change":1000.0,"close_price":6250.0,"amount_change":6250000.0},{"trade_date":"2026-07-23","etf_code":"00984A","stock_code":"6531","stock_name":"愛普科技","action":"INCREASE","weight_before":1.11,"weight_after":1.17,"weight_change":0.06,"shares_change":3000.0,"close_price":908.0,"amount_change":2724000.0},{"trade_date":"2026-07-23","etf_code":"00985A","stock_code":"2330","stock_name":"台灣積體電路製造","action":"DECREASE","weight_before":21.66,"weight_after":18.18,"weight_change":-3.48,"shares_change":-148000.0,"close_price":2400.0,"amount_change":-355200000.0},{"trade_date":"2026-07-23","etf_code":"00985A","stock_code":"3036","stock_name":"文曄科技","action":"INCREASE","weight_before":2.45,"weight_after":2.61,"weight_change":0.16,"shares_change":19000.0,"close_price":197.5,"amount_change":3752500.0},{"trade_date":"2026-07-23","etf_code":"00985A","stock_code":"3665","stock_name":"貿聯控股（BizLink Holding In","action":"INCREASE","weight_before":0.27,"weight_after":0.98,"weight_change":0.71,"shares_change":30000.0,"close_price":2115.0,"amount_change":63450000.0},{"trade_date":"2026-07-23","etf_code":"00985A","stock_code":"6442","stock_name":"光紅建聖","action":"INCREASE","weight_before":3.22,"weight_after":3.36,"weight_change":0.14,"shares_change":9000.0,"close_price":1385.0,"amount_change":12465000.0},{"trade_date":"2026-07-23","etf_code":"00987A","stock_code":"2454","stock_name":"聯發科","action":"INCREASE","weight_before":3.59,"weight_after":4.77,"weight_change":1.18,"shares_change":8000.0,"close_price":3850.0,"amount_change":30800000.0},{"trade_date":"2026-07-23","etf_code":"00987A","stock_code":"6739","stock_name":"竹陞科技","action":"NEW_BUY","weight_before":0.0,"weight_after":0.92,"weight_change":0.92,"shares_change":20000.0,"close_price":1190.0,"amount_change":23800000.0},{"trade_date":"2026-07-23","etf_code":"00987A","stock_code":"7769","stock_name":"鴻勁","action":"INCREASE","weight_before":1.24,"weight_after":2.49,"weight_change":1.25,"shares_change":5000.0,"close_price":6405.0,"amount_change":32025000.0},{"trade_date":"2026-07-23","etf_code":"00988A","stock_code":"2308","stock_name":"台達電","action":"INCREASE","weight_before":0.55,"weight_after":1.01,"weight_change":0.46,"shares_change":145000.0,"close_price":1880.0,"amount_change":272600000.0},{"trade_date":"2026-07-23","etf_code":"00988A","stock_code":"3665","stock_name":"貿聯-KY","action":"INCREASE","weight_before":0.43,"weight_after":0.89,"weight_change":0.46,"shares_change":124000.0,"close_price":2115.0,"amount_change":262260000.0},{"trade_date":"2026-07-23","etf_code":"00988A","stock_code":"6223","stock_name":"旺矽","action":"INCREASE","weight_before":1.45,"weight_after":1.92,"weight_change":0.47,"shares_change":45000.0,"close_price":6250.0,"amount_change":281250000.0},{"trade_date":"2026-07-23","etf_code":"00991A","stock_code":"1303","stock_name":"南亞塑膠","action":"INCREASE","weight_before":1.28,"weight_after":1.52,"weight_change":0.24,"shares_change":1200000.0,"close_price":208.0,"amount_change":249600000.0},{"trade_date":"2026-07-23","etf_code":"00991A","stock_code":"2308","stock_name":"台達電子","action":"INCREASE","weight_before":1.47,"weight_after":1.59,"weight_change":0.12,"shares_change":50000.0,"close_price":1880.0,"amount_change":94000000.0},{"trade_date":"2026-07-23","etf_code":"00991A","stock_code":"2330","stock_name":"台灣積體","action":"DECREASE","weight_before":12.63,"weight_after":12.36,"weight_change":-0.27,"shares_change":-100000.0,"close_price":2400.0,"amount_change":-240000000.0},{"trade_date":"2026-07-23","etf_code":"00991A","stock_code":"3665","stock_name":"貿聯-KY","action":"INCREASE","weight_before":1.52,"weight_after":1.73,"weight_change":0.21,"shares_change":30000.0,"close_price":2115.0,"amount_change":63450000.0},{"trade_date":"2026-07-23","etf_code":"00993A","stock_code":"1301","stock_name":"台塑","action":"INCREASE","weight_before":0.23,"weight_after":0.43,"weight_change":0.2,"shares_change":330000.0,"close_price":63.5,"amount_change":20955000.0},{"trade_date":"2026-07-23","etf_code":"00993A","stock_code":"1303","stock_name":"南亞","action":"INCREASE","weight_before":0.61,"weight_after":0.9,"weight_change":0.29,"shares_change":134000.0,"close_price":208.0,"amount_change":27872000.0},{"trade_date":"2026-07-23","etf_code":"00993A","stock_code":"1590","stock_name":"亞德客-KY","action":"FULL_SELL","weight_before":0.13,"weight_after":0.0,"weight_change":-0.13,"shares_change":-9000.0,"close_price":1430.0,"amount_change":-12870000.0},{"trade_date":"2026-07-23","etf_code":"00993A","stock_code":"2027","stock_name":"大成鋼","action":"INCREASE","weight_before":0.24,"weight_after":0.45,"weight_change":0.21,"shares_change":459000.0,"close_price":43.75,"amount_change":20081250.0},{"trade_date":"2026-07-23","etf_code":"00993A","stock_code":"2303","stock_name":"聯電","action":"DECREASE","weight_before":2.9,"weight_after":2.62,"weight_change":-0.28,"shares_change":-197000.0,"close_price":139.0,"amount_change":-27383000.0},{"trade_date":"2026-07-23","etf_code":"00993A","stock_code":"2308","stock_name":"台達電子","action":"DECREASE","weight_before":2.96,"weight_after":2.87,"weight_change":-0.09,"shares_change":-3000.0,"close_price":1880.0,"amount_change":-5640000.0},{"trade_date":"2026-07-23","etf_code":"00993A","stock_code":"2327","stock_name":"國巨*","action":"DECREASE","weight_before":3.25,"weight_after":2.58,"weight_change":-0.67,"shares_change":-102000.0,"close_price":703.0,"amount_change":-71706000.0},{"trade_date":"2026-07-23","etf_code":"00993A","stock_code":"2330","stock_name":"台積電","action":"INCREASE","weight_before":12.81,"weight_after":13.62,"weight_change":0.81,"shares_change":54000.0,"close_price":2400.0,"amount_change":129600000.0},{"trade_date":"2026-07-23","etf_code":"00993A","stock_code":"2345","stock_name":"智邦","action":"DECREASE","weight_before":3.72,"weight_after":2.86,"weight_change":-0.86,"shares_change":-37000.0,"close_price":2285.0,"amount_change":-84545000.0},{"trade_date":"2026-07-23","etf_code":"00993A","stock_code":"2360","stock_name":"致茂","action":"INCREASE","weight_before":0.87,"weight_after":1.69,"weight_change":0.82,"shares_change":38000.0,"close_price":2125.0,"amount_change":80750000.0},{"trade_date":"2026-07-23","etf_code":"00993A","stock_code":"2368","stock_name":"金像電子","action":"DECREASE","weight_before":1.56,"weight_after":1.27,"weight_change":-0.29,"shares_change":-19000.0,"close_price":940.0,"amount_change":-17860000.0},{"trade_date":"2026-07-23","etf_code":"00993A","stock_code":"2383","stock_name":"台光電子","action":"DECREASE","weight_before":4.46,"weight_after":3.87,"weight_change":-0.59,"shares_change":-14000.0,"close_price":5125.0,"amount_change":-71750000.0},{"trade_date":"2026-07-23","etf_code":"00993A","stock_code":"2395","stock_name":"研華","action":"INCREASE","weight_before":0.28,"weight_after":0.58,"weight_change":0.3,"shares_change":50000.0,"close_price":596.0,"amount_change":29800000.0},{"trade_date":"2026-07-23","etf_code":"00993A","stock_code":"2412","stock_name":"中華電","action":"INCREASE","weight_before":0.27,"weight_after":0.49,"weight_change":0.22,"shares_change":170000.0,"close_price":138.5,"amount_change":23545000.0},{"trade_date":"2026-07-23","etf_code":"00993A","stock_code":"2454","stock_name":"聯發科","action":"DECREASE","weight_before":5.13,"weight_after":4.36,"weight_change":-0.77,"shares_change":-22000.0,"close_price":3850.0,"amount_change":-84700000.0},{"trade_date":"2026-07-23","etf_code":"00993A","stock_code":"2472","stock_name":"立隆","action":"FULL_SELL","weight_before":0.14,"weight_after":0.0,"weight_change":-0.14,"shares_change":-49000.0,"close_price":282.5,"amount_change":-13842500.0},{"trade_date":"2026-07-23","etf_code":"00993A","stock_code":"2618","stock_name":"長榮航","action":"INCREASE","weight_before":0.51,"weight_after":0.57,"weight_change":0.06,"shares_change":198000.0,"close_price":42.1,"amount_change":8335800.0},{"trade_date":"2026-07-23","etf_code":"00993A","stock_code":"2637","stock_name":"慧洋-KY","action":"INCREASE","weight_before":0.32,"weight_after":0.6,"weight_change":0.28,"shares_change":336000.0,"close_price":83.6,"amount_change":28089600.0},{"trade_date":"2026-07-23","etf_code":"00993A","stock_code":"2881","stock_name":"富邦金控","action":"INCREASE","weight_before":0.88,"weight_after":1.16,"weight_change":0.28,"shares_change":225000.0,"close_price":127.0,"amount_change":28575000.0},{"trade_date":"2026-07-23","etf_code":"00993A","stock_code":"2882","stock_name":"國泰金","action":"INCREASE","weight_before":0.28,"weight_after":0.52,"weight_change":0.24,"shares_change":255000.0,"close_price":96.8,"amount_change":24684000.0},{"trade_date":"2026-07-23","etf_code":"00993A","stock_code":"2883","stock_name":"凱基金控","action":"INCREASE","weight_before":1.49,"weight_after":1.96,"weight_change":0.47,"shares_change":1593000.0,"close_price":30.45,"amount_change":48506850.0},{"trade_date":"2026-07-23","etf_code":"00993A","stock_code":"2885","stock_name":"元大金","action":"INCREASE","weight_before":1.03,"weight_after":1.08,"weight_change":0.05,"shares_change":87000.0,"close_price":63.1,"amount_change":5489700.0},{"trade_date":"2026-07-23","etf_code":"00993A","stock_code":"2890","stock_name":"永豐金控","action":"INCREASE","weight_before":1.12,"weight_after":1.41,"weight_change":0.29,"shares_change":802000.0,"close_price":40.4,"amount_change":32400800.0},{"trade_date":"2026-07-23","etf_code":"00993A","stock_code":"2891","stock_name":"中信金","action":"INCREASE","weight_before":0.64,"weight_after":0.71,"weight_change":0.07,"shares_change":120000.0,"close_price":64.0,"amount_change":7680000.0},{"trade_date":"2026-07-23","etf_code":"00993A","stock_code":"3017","stock_name":"奇鋐","action":"DECREASE","weight_before":3.1,"weight_after":2.09,"weight_change":-1.01,"shares_change":-37000.0,"close_price":2265.0,"amount_change":-83805000.0},{"trade_date":"2026-07-23","etf_code":"00993A","stock_code":"3023","stock_name":"信邦","action":"FULL_SELL","weight_before":0.13,"weight_after":0.0,"weight_change":-0.13,"shares_change":-41000.0,"close_price":317.0,"amount_change":-12997000.0},{"trade_date":"2026-07-23","etf_code":"00993A","stock_code":"3037","stock_name":"欣興","action":"DECREASE","weight_before":3.32,"weight_after":2.71,"weight_change":-0.61,"shares_change":-91000.0,"close_price":907.0,"amount_change":-82537000.0},{"trade_date":"2026-07-23","etf_code":"00993A","stock_code":"3042","stock_name":"晶技","action":"FULL_SELL","weight_before":0.16,"weight_after":0.0,"weight_change":-0.16,"shares_change":-94000.0,"close_price":169.0,"amount_change":-15886000.0},{"trade_date":"2026-07-23","etf_code":"00993A","stock_code":"3264","stock_name":"欣銓","action":"INCREASE","weight_before":0.82,"weight_after":1.25,"weight_change":0.43,"shares_change":203000.0,"close_price":218.0,"amount_change":44254000.0},{"trade_date":"2026-07-23","etf_code":"00993A","stock_code":"3443","stock_name":"創意電子","action":"NEW_BUY","weight_before":0.0,"weight_after":1.34,"weight_change":1.34,"shares_change":31000.0,"close_price":4370.0,"amount_change":135470000.0},{"trade_date":"2026-07-23","etf_code":"00993A","stock_code":"3653","stock_name":"健策","action":"INCREASE","weight_before":0.69,"weight_after":1.35,"weight_change":0.66,"shares_change":20000.0,"close_price":3500.0,"amount_change":70000000.0},{"trade_date":"2026-07-23","etf_code":"00993A","stock_code":"3665","stock_name":"貿聯-KY","action":"FULL_SELL","weight_before":1.17,"weight_after":0.0,"weight_change":-1.17,"shares_change":-57000.0,"close_price":2115.0,"amount_change":-120555000.0},{"trade_date":"2026-07-23","etf_code":"00993A","stock_code":"3702","stock_name":"大聯大","action":"INCREASE","weight_before":0.55,"weight_after":0.67,"weight_change":0.12,"shares_change":93000.0,"close_price":118.0,"amount_change":10974000.0},{"trade_date":"2026-07-23","etf_code":"00993A","stock_code":"3711","stock_name":"日月光投控","action":"DECREASE","weight_before":2.81,"weight_after":2.53,"weight_change":-0.28,"shares_change":-45000.0,"close_price":656.0,"amount_change":-29520000.0},{"trade_date":"2026-07-23","etf_code":"00993A","stock_code":"4904","stock_name":"遠傳","action":"INCREASE","weight_before":0.51,"weight_after":0.57,"weight_change":0.06,"shares_change":70000.0,"close_price":103.0,"amount_change":7210000.0},{"trade_date":"2026-07-23","etf_code":"00993A","stock_code":"5289","stock_name":"宜鼎國際","action":"FULL_SELL","weight_before":0.17,"weight_after":0.0,"weight_change":-0.17,"shares_change":-13000.0,"close_price":1370.0,"amount_change":-17810000.0},{"trade_date":"2026-07-23","etf_code":"00993A","stock_code":"5536","stock_name":"聖暉*","action":"FULL_SELL","weight_before":1.28,"weight_after":0.0,"weight_change":-1.28,"shares_change":-105000.0,"close_price":1195.0,"amount_change":-125475000.0},{"trade_date":"2026-07-23","etf_code":"00993A","stock_code":"5904","stock_name":"寶雅","action":"FULL_SELL","weight_before":0.29,"weight_after":0.0,"weight_change":-0.29,"shares_change":-44000.0,"close_price":635.0,"amount_change":-27940000.0},{"trade_date":"2026-07-23","etf_code":"00993A","stock_code":"6213","stock_name":"聯茂","action":"FULL_SELL","weight_before":0.18,"weight_after":0.0,"weight_change":-0.18,"shares_change":-50000.0,"close_price":367.0,"amount_change":-18350000.0},{"trade_date":"2026-07-23","etf_code":"00993A","stock_code":"6223","stock_name":"旺矽","action":"INCREASE","weight_before":5.49,"weight_after":5.84,"weight_change":0.35,"shares_change":7000.0,"close_price":6250.0,"amount_change":43750000.0},{"trade_date":"2026-07-23","etf_code":"00993A","stock_code":"6446","stock_name":"藥華醫藥","action":"INCREASE","weight_before":0.86,"weight_after":0.92,"weight_change":0.06,"shares_change":7000.0,"close_price":1180.0,"amount_change":8260000.0},{"trade_date":"2026-07-23","etf_code":"00993A","stock_code":"6488","stock_name":"環球晶圓","action":"INCREASE","weight_before":0.66,"weight_after":1.1,"weight_change":0.44,"shares_change":36000.0,"close_price":1120.0,"amount_change":40320000.0},{"trade_date":"2026-07-23","etf_code":"00993A","stock_code":"6669","stock_name":"緯穎","action":"DECREASE","weight_before":2.57,"weight_after":2.02,"weight_change":-0.55,"shares_change":-13000.0,"close_price":5500.0,"amount_change":-71500000.0},{"trade_date":"2026-07-23","etf_code":"00993A","stock_code":"7769","stock_name":"鴻勁","action":"INCREASE","weight_before":1.13,"weight_after":1.91,"weight_change":0.78,"shares_change":13000.0,"close_price":6405.0,"amount_change":83265000.0},{"trade_date":"2026-07-23","etf_code":"00993A","stock_code":"8150","stock_name":"南茂科技","action":"FULL_SELL","weight_before":0.16,"weight_after":0.0,"weight_change":-0.16,"shares_change":-147000.0,"close_price":100.0,"amount_change":-14700000.0},{"trade_date":"2026-07-23","etf_code":"00993A","stock_code":"8358","stock_name":"金居開發","action":"INCREASE","weight_before":0.48,"weight_after":0.88,"weight_change":0.4,"shares_change":98000.0,"close_price":406.5,"amount_change":39837000.0},{"trade_date":"2026-07-23","etf_code":"00994A","stock_code":"1303","stock_name":"南亞","action":"NEW_BUY","weight_before":0.0,"weight_after":0.33,"weight_change":0.33,"shares_change":80000.0,"close_price":208.0,"amount_change":16640000.0},{"trade_date":"2026-07-23","etf_code":"00994A","stock_code":"2303","stock_name":"聯電","action":"INCREASE","weight_before":0.9,"weight_after":1.01,"weight_change":0.11,"shares_change":40000.0,"close_price":139.0,"amount_change":5560000.0},{"trade_date":"2026-07-23","etf_code":"00994A","stock_code":"2308","stock_name":"台達電","action":"INCREASE","weight_before":2.27,"weight_after":2.82,"weight_change":0.55,"shares_change":15000.0,"close_price":1880.0,"amount_change":28200000.0},{"trade_date":"2026-07-23","etf_code":"00994A","stock_code":"2360","stock_name":"致茂","action":"INCREASE","weight_before":0.88,"weight_after":1.75,"weight_change":0.87,"shares_change":20000.0,"close_price":2125.0,"amount_change":42500000.0},{"trade_date":"2026-07-23","etf_code":"00994A","stock_code":"2383","stock_name":"台光電","action":"INCREASE","weight_before":7.04,"weight_after":7.73,"weight_change":0.69,"shares_change":5000.0,"close_price":5125.0,"amount_change":25625000.0},{"trade_date":"2026-07-23","etf_code":"00994A","stock_code":"2454","stock_name":"聯發科","action":"INCREASE","weight_before":6.65,"weight_after":7.12,"weight_change":0.47,"shares_change":5000.0,"close_price":3850.0,"amount_change":19250000.0},{"trade_date":"2026-07-23","etf_code":"00994A","stock_code":"8046","stock_name":"南電","action":"INCREASE","weight_before":5.83,"weight_after":6.19,"weight_change":0.36,"shares_change":1000.0,"close_price":1305.0,"amount_change":1305000.0},{"trade_date":"2026-07-23","etf_code":"00995A","stock_code":"2486","stock_name":"一詮精密工業","action":"INCREASE","weight_before":0.47,"weight_after":0.72,"weight_change":0.25,"shares_change":50000.0,"close_price":232.5,"amount_change":11625000.0},{"trade_date":"2026-07-23","etf_code":"00995A","stock_code":"6147","stock_name":"頎邦科技","action":"DECREASE","weight_before":0.46,"weight_after":0.21,"weight_change":-0.25,"shares_change":-60000.0,"close_price":175.5,"amount_change":-10530000.0},{"trade_date":"2026-07-23","etf_code":"00995A","stock_code":"6510","stock_name":"中華精測科技","action":"FULL_SELL","weight_before":0.27,"weight_after":0.0,"weight_change":-0.27,"shares_change":-5000.0,"close_price":2760.0,"amount_change":-13800000.0},{"trade_date":"2026-07-23","etf_code":"00996A","stock_code":"3363","stock_name":"上詮","action":"NEW_BUY","weight_before":0.0,"weight_after":0.1,"weight_change":0.1,"shares_change":7000.0,"close_price":589.0,"amount_change":4123000.0},{"trade_date":"2026-07-23","etf_code":"00996A","stock_code":"6274","stock_name":"台燿","action":"NEW_BUY","weight_before":0.0,"weight_after":0.18,"weight_change":0.18,"shares_change":6000.0,"close_price":1335.0,"amount_change":8010000.0},{"trade_date":"2026-07-23","etf_code":"00996A","stock_code":"6510","stock_name":"精測","action":"DECREASE","weight_before":0.66,"weight_after":0.25,"weight_change":-0.41,"shares_change":-7000.0,"close_price":2760.0,"amount_change":-19320000.0},{"trade_date":"2026-07-23","etf_code":"00996A","stock_code":"8021","stock_name":"尖點","action":"INCREASE","weight_before":1.15,"weight_after":1.32,"weight_change":0.17,"shares_change":20000.0,"close_price":418.5,"amount_change":8370000.0},{"trade_date":"2026-07-23","etf_code":"00996A","stock_code":"8046","stock_name":"南電","action":"DECREASE","weight_before":5.07,"weight_after":4.33,"weight_change":-0.74,"shares_change":-19000.0,"close_price":1305.0,"amount_change":-24795000.0},{"trade_date":"2026-07-23","etf_code":"00999A","stock_code":"2890","stock_name":"永豐金融控股","action":"DECREASE","weight_before":1.26,"weight_after":1.21,"weight_change":-0.05,"shares_change":78780.0,"close_price":40.4,"amount_change":3182712.0}]