[
  {
    "stock_code": "2368",
    "stock_name": "金像電",
    "etf_count": 2,
    "value": -1451800000.0,
    "etf_list": [
      "00403A",
      "00992A"
    ]
  },
  {
    "stock_code": "3105",
    "stock_name": "穩懋",
    "etf_count": 1,
    "value": -397992000.0,
    "etf_list": [
      "00992A"
    ]
  },
  {
    "stock_code": "2308",
    "stock_name": "台達電",
    "etf_count": 1,
    "value": -316750000.0,
    "etf_list": [
      "00988A"
    ]
  },
  {
    "stock_code": "6510",
    "stock_name": "精測",
    "etf_count": 1,
    "value": -303500000.0,
    "etf_list": [
      "00981A"
    ]
  },
  {
    "stock_code": "5274",
    "stock_name": "信驊",
    "etf_count": 1,
    "value": -258570000.0,
    "etf_list": [
      "00988A"
    ]
  },
  {
    "stock_code": "6515",
    "stock_name": "穎崴",
    "etf_count": 1,
    "value": -212940000.0,
    "etf_list": [
      "00988A"
    ]
  },
  {
    "stock_code": "2330",
    "stock_name": "台灣積體電路製造",
    "etf_count": 2,
    "value": -184860000.0,
    "etf_list": [
      "00980A",
      "00995A"
    ]
  },
  {
    "stock_code": "3665",
    "stock_name": "貿聯-KY",
    "etf_count": 2,
    "value": -170660000.0,
    "etf_list": [
      "00403A",
      "00994A"
    ]
  },
  {
    "stock_code": "2360",
    "stock_name": "致茂",
    "etf_count": 1,
    "value": -101750000.0,
    "etf_list": [
      "00992A"
    ]
  },
  {
    "stock_code": "6223",
    "stock_name": "旺矽科技",
    "etf_count": 1,
    "value": -48480000.0,
    "etf_list": [
      "00980A"
    ]
  },
  {
    "stock_code": "3081",
    "stock_name": "聯亞",
    "etf_count": 1,
    "value": -42735000.0,
    "etf_list": [
      "00996A"
    ]
  },
  {
    "stock_code": "6187",
    "stock_name": "萬潤",
    "etf_count": 1,
    "value": -35280000.0,
    "etf_list": [
      "00987A"
    ]
  },
  {
    "stock_code": "4979",
    "stock_name": "華星光通科技",
    "etf_count": 1,
    "value": -18716500.0,
    "etf_list": [
      "00995A"
    ]
  },
  {
    "stock_code": "6223",
    "stock_name": "旺矽",
    "etf_count": 1,
    "value": -18180000.0,
    "etf_list": [
      "00994A"
    ]
  },
  {
    "stock_code": "2308",
    "stock_name": "台達電子工業",
    "etf_count": 1,
    "value": -18100000.0,
    "etf_list": [
      "00995A"
    ]
  },
  {
    "stock_code": "2882",
    "stock_name": "國泰金融控股",
    "etf_count": 1,
    "value": -11978000.0,
    "etf_list": [
      "00401A"
    ]
  },
  {
    "stock_code": "6147",
    "stock_name": "頎邦",
    "etf_count": 1,
    "value": -7807000.0,
    "etf_list": [
      "00994A"
    ]
  },
  {
    "stock_code": "7751",
    "stock_name": "竑騰",
    "etf_count": 1,
    "value": -3990000.0,
    "etf_list": [
      "00995A"
    ]
  },
  {
    "stock_code": "5536",
    "stock_name": "聖暉*",
    "etf_count": 1,
    "value": -1245000.0,
    "etf_list": [
      "00982A"
    ]
  }
]